[
  {
    "img": "blog_8933246523.jpg",
    "date": "2026.03",
    "place": "안산 네일아트샵",
    "spec": "LG 4WAY 25평 1등급 정부지원 냉난방기 신규 설치",
    "type": "4WAY",
    "blogImg": "/images/blog-cases/blog_8933246523.jpg",
    "excerpt": "안산 원타상가 1층에 위치한 A 네일아트샵 현장에 도착했을 때, 가장 먼저 눈에 들어온 것은 완성도 높은 인테리어였다. 화이트 톤 벽면에 LED 간접조명, 타원형 백라이트 거울, 라운드 선반까지 — 신규 오픈을 앞둔 매장 특유의 깔끔한 마감이 인상적이었다. 안산 에어컨설치 전문 디디에어컨이 이 현장에 투입된 이유는 명확했다. 천장에 4WAY 카세트용 개구부가 미리 타공되어 있었고, 배관 선작업까지 완료된 상태에서 에어컨 본체 설치만 남아 있었다. 네일아트 업종은 시술 환경의 온도 관리가 매출에 직",
    "blogLink": "https://blog.naver.com/ddinair/224226700322?fromRss=true&trackingCode=rss"
  },
  {
    "img": "blog_708380307.jpg",
    "date": "2026.03",
    "place": "강변 치과",
    "spec": "삼성 4WAY 30평 냉난방기 1등급 정부지원 교체 시공",
    "type": "4WAY",
    "blogImg": "/images/blog-cases/blog_708380307.jpg",
    "excerpt": "기존 설비 진단 결과부터 확인하겠습니다. 서울 광진구 강변 인근 S 치과&피부과에서 운용 중인 삼성 천장형 4WAY 카세트 에어컨의 성능 저하가 심각한 수준이었습니다. 냉난방 효율이 눈에 띄게 떨어진 상태였으며, 실외기 트리플팬 유닛의 노후화가 진행되어 소음과 진동이 증가한 상황이었습니다. 강변 에어컨설치 전문 디디에어컨에서 현장 점검을 실시한 결과, 기존 장비의 수리보다 신규 교체가 경제적으로 합리적이라는 판단을 내렸습니다. 치과는 환자 진료 환경의 특수성상 실내 온도 관리가 매우 중요한 업종입",
    "blogLink": "https://blog.naver.com/ddinair/224226658954?fromRss=true&trackingCode=rss"
  },
  {
    "img": "blog_8092337726.jpg",
    "date": "2026.03",
    "place": "마포 사무실",
    "spec": "LG 4WAY 천장형 25평 + 위니아 벽걸이 16평 냉난방 설치",
    "type": "4WAY",
    "blogImg": "/images/blog-cases/blog_8092337726.jpg",
    "excerpt": "겨울이 끝나기 전에 냉난방 시스템을 세팅해두면 여름 성수기 대비가 가능하고, 시공 일정도 여유롭게 잡을 수 있습니다. 마포 소재 한 사무실에서 인테리어 리모델링과 동시에 에어컨 교체를 의뢰해 오셨습니다. 사무 공간에는 LG 4WAY 천장형 25평 냉난방, 별도 공간에는 위니아 벽걸이 16평 냉난방을 각각 설치하는 조합이었습니다. 마포에어컨설치 전문 디디에어컨이 두 대 동시 시공을 진행한 사례를 기록합니다. ■ 현장 진단 및 장비 선정 메인 사무 공간은 약 25평 규모의 오픈 플로어 구조였습니다. ",
    "blogLink": "https://blog.naver.com/ddinair/224220317824?fromRss=true&trackingCode=rss"
  },
  {
    "img": "blog_4514050969.jpg",
    "date": "2026.03",
    "place": "안양 부영7단지 아파트",
    "spec": "LG 1WAY 천장형 냉방전용 에어컨 설치",
    "type": "1WAY",
    "blogImg": "/images/blog-cases/blog_4514050969.jpg",
    "excerpt": "거실 면적 대비 효율적인 냉방을 원하지만, 벽걸이는 인테리어와 맞지 않는다는 요구가 아파트 현장에서 자주 발생한다. 안양 부영7단지의 이번 현장도 동일한 조건이었다. 기존 거실 공간에 벽걸이 에어컨 대신 천장형 1WAY 냉방전용 모델을 설치해 달라는 요청이었다. 안양에어컨설치 전문 디디에어컨이 LG 1WAY 15평 천장형 냉방전용 에어컨 1조를 시공한 사례를 기록한다. ■ 현장 진단조였다. 1WAY 천장형 모델을 선택한 이유는 명확했다. 첫째, 한 방향 집중 토출로 거실 전체를 커버할 수 있다. ",
    "blogLink": "https://blog.naver.com/ddinair/224219071823?fromRss=true&trackingCode=rss"
  },
  {
    "img": "blog_3469227169.jpg",
    "date": "2026.03",
    "place": "수원 인계동 에어컨 이전설치 1층 카페 천장형 실내기 위치 변경 및 배관 작업",
    "spec": "",
    "type": "기타",
    "blogImg": "/images/blog-cases/blog_3469227169.jpg",
    "excerpt": "상업 공간의 인테리어 변경 시 가장 먼저 선행되어야 하는 것이 공조 설비의 재배치입니다. 이번 현장은 수원 인계로에 위치한 1층 상가 카페로, 새로운 동선과 공간 활용을 위해 기존 천장형 실내기의 위치를 변경하는 에어컨 이전설치 작업이 진행되었습니다. 카페와 같은 1층 상업 시설은 층고가 높고 개방감이 있어 냉난방 효율을 극대화할 수 있는 정확한 위치 선정이 필수적입니다. 단순히 기계를 옮기는 것이 아니라, 연장되는 배관의 압력 손실을 최소화하고 원활한 배수(드레인) 구배를 다시 잡는 고난도 기초",
    "blogLink": "https://blog.naver.com/ddinair/224207115311?fromRss=true&trackingCode=rss"
  },
  {
    "img": "blog_1718643263.jpg",
    "date": "2026.03",
    "place": "서초구 잠원동 오피스 원복 현장 시스템에어컨",
    "spec": "LG 멀티V S 4Way 정밀 시공 사례",
    "type": "멀티",
    "blogImg": "/images/blog-cases/blog_1718643263.jpg",
    "excerpt": "상업용 오피스 공간의 임대차 계약 종료나 구조 변경 시 진행되는 원복(원상복구) 공사는 기존 인테리어를 철거하고 기본 뼈대를 되살리는 과정이다. 이때 가장 핵심이 되는 설비가 바로 냉난방 시스템의 재구축이다. 이번 현장은 서초구 잠원동(신반포로)에 위치한 3층 사무실 원복 현장으로, 넓은 오픈형 데스크 공간을 커버하기 위해 30평형 멀티 4way 천장형 실내기 2대와 대용량 실외기 1대가 매칭된 시스템 에어컨 신규설치 작업이 진행되었다. 사무실 환경 특성상 배관 노출을 없애고 전력 부하를 분산시키",
    "blogLink": "https://blog.naver.com/ddinair/224207098540?fromRss=true&trackingCode=rss"
  },
  {
    "img": "blog_2890864003.jpg",
    "date": "2026.03",
    "place": "서초 신반포 에어컨 이전설치 상업시설 천장형 멀티 시스템 변경 작업",
    "spec": "",
    "type": "멀티",
    "blogImg": "/images/blog-cases/blog_2890864003.jpg",
    "excerpt": "서초구 신반포로에 위치한 3층 상업시설 현장입니다. 기존에 사용하던 30평형 4way 제품 1대를 철거하고, 각 공간의 독립적인 온도 제어를 위해 5평형 1way 실내기 5대와 10마력 멀티 실외기를 조합하는 대대적인 설비 변경이 진행되었습니다. 단일 대형 기기에서 다수 소형 기기로 분할하여 설치하는 경우, 천장 내부 배관 라인 재설정과 분전반의 전기 용량 확보가 작업의 핵심입니다. 새로운 멀티 시스템의 전력 부하를 감당하기 위한 메인 50A 및 하위 20A 차단기 점검 사진 STEP 1. 기존 ",
    "blogLink": "https://blog.naver.com/ddinair/224204374966?fromRss=true&trackingCode=rss"
  },
  {
    "img": "blog_6245911954.jpg",
    "date": "2026.03",
    "place": "강동구 에어컨 신규설치 상가 지하 관리실 3상 동력선 및 배관 시공",
    "spec": "",
    "type": "기타",
    "blogImg": "/images/blog-cases/blog_6245911954.jpg",
    "excerpt": "강동구 에어컨 신규설치 지하 관리실 3상 동력선 및 배관 시공 상업 시설 내 관리실, 특히 지하에 위치한 공간은 자연 환기가 불가능하고 24시간 일정한 온도 유지가 필수적인 특수 환경입니다. 이번 현장은 강동구에 위치한 대형 상가 지하 관리실로, 근무자들의 쾌적한 환경 조성과 시설물 보호를 위해 상업용 대용량 냉난방기 신규설치가 진행되었습니다. 단순한 가정용 장비와 달리 상업용 기기 신규설치는 3상 전력망의 안전한 구축과 공간 특성에 맞는 배관 경로 설계가 시스템의 수명과 직결됩니다. 지하 밀폐 ",
    "blogLink": "https://blog.naver.com/ddinair/224204211370?fromRss=true&trackingCode=rss"
  },
  {
    "img": "blog_9437072378.jpg",
    "date": "2026.02",
    "place": "서울 광진구 A 헤어샵건대점 시스템에어컨 40평/28평 조합 설치 - 인테리어의 완성은 공조 설계다",
    "spec": "",
    "type": "기타",
    "blogImg": "/images/blog-cases/blog_9437072378.jpg",
    "excerpt": "공조 설비는 공간의 미학과 기능성을 완성하는 뼈대입니다. 특히 천장이 그대로 드러나는 오픈 천장 인테리어의 경우, 시스템에어컨의 배관 라인과 안착 위치가 곧 인테리어의 마감 퀄리티를 직결합니다. 이번 현장은 서울 광진구 건대 인근에 신규 오픈하는 'A헤어' 리모델링 현장으로, 엄격한 공정 관리를 통해 LG 4WAY 시스템에어컨을 정밀하게 안착시킨 시공 사례입니다. [시공 전]: 현장 진단 및 기류 설계 방안 본격적인 인테리어 공정이 시작되기 전, 뼈대만 남은 현장에 투입되어 구조 진단을 실시했습니",
    "blogLink": "https://blog.naver.com/ddinair/224181312738?fromRss=true&trackingCode=rss"
  },
  {
    "img": "blog_6687684293.jpg",
    "date": "2026.02",
    "place": "서울 강동구 s식당 주방",
    "spec": "LG 13평 벽걸이 에어컨 설치 - 영업 종료 후 야간 시공의 정석",
    "type": "벽걸이",
    "blogImg": "/images/blog-cases/blog_6687684293.jpg",
    "excerpt": "강동구 S 주방 에어컨 설치 완료했습니다 S주방 강동역점 현장이었습니다. 주방에 LG 휘센 벽걸이 13평형 설치하는 거였어요. 11월 26일 수요일이었는데 식당이라 영업 끝나고 작업 들어갔습니다. 점심이랑 저녁 피크타임에는 손님 많아서 도저히 작업 못 하거든요. 주방은 진짜 뜨거워요. 화구 열기랑 식기세척기 스팀 때문에 겨울에도 땀 나는 곳이거든요. 셰프님들 컨디션이 음식 맛에 직결되니까 에어컨 설치가 필수죠. 강동파밀리에 상가 안에 있는 매장이었어요. 도착하자마자 제일 어려운 외부 배관 작업부터",
    "blogLink": "https://blog.naver.com/ddinair/224176144251?fromRss=true&trackingCode=rss"
  },
  {
    "img": "blog_8891667018.jpg",
    "date": "2026.02",
    "place": "마포 연남동 c카페",
    "spec": "LG 컨버터블 23평 + 벽걸이 16평",
    "type": "벽걸이",
    "blogImg": "/images/blog-cases/blog_8891667018.jpg",
    "excerpt": "상업 공간의 냉난방기 설계는 단순한 기기 설치를 넘어, 매장의 구조적 특성과 영업 환경을 고려한 종합 엔지니어링입니다. 특히 유동 인구가 많은 상권의 노출 천장 인테리어 현장은 고도의 기술력과 유연한 시공 대처 능력이 요구됩니다. 이번 포스팅에서는 마포 연남동 카페 현장의 야간 시공 사례를 통해, 직사각형 상업 공간에 최적화된 냉난방 설계 및 정석 시공에 대한 필수 정보를 전달해 드립니다. [시공 전]: 현장 진단 및 야간 시공 설계 해당 현장은 마포 연남동의 중심 상권에 위치한 C카페입니다. 주",
    "blogLink": "https://blog.naver.com/ddinair/224173692867?fromRss=true&trackingCode=rss"
  },
  {
    "img": "blog_2887410509.jpg",
    "date": "2026.02",
    "place": "하남 감이동 D헤어샵 2층",
    "spec": "LG 4WAY 1등급 냉난방기 1조 신규 설치",
    "type": "4WAY",
    "blogImg": "/images/blog-cases/blog_2887410509.jpg",
    "excerpt": "헤어샵(미용실)은 헤어드라이어와 세팅기 등 열원 기구의 사용이 잦고, 화학 약품 냄새로 인해 환기 및 공조 설계의 난이도가 높은 상업 공간입니다. 이번 현장은 하남시 감이동에 신규 오픈하는 D헤어샵 2층으로, 인테리어 공정 단계에 투입되어 기류의 사각지대를 없애고 에너지 효율을 극대화한 LG 1등급 4WAY 냉난방기 신규 설치 사례입니다. [시공 전]: 현장 진단 및 고객 요청사항 현장 도착 직후 천장 구조부터 정밀하게 스캔했습니다. 해당 공간은 텍스(Tex) 마감 천장으로, 레이저 레벨기를 띄워",
    "blogLink": "https://blog.naver.com/ddinair/224172968666?fromRss=true&trackingCode=rss"
  },
  {
    "img": "blog_3543108519.jpg",
    "date": "2026.02",
    "place": "파주 B금고",
    "spec": "LG 4WAY 냉난방기 총 4조(25평형 2조 + 15평형 2조) 신축 현장 완벽 시공",
    "type": "4WAY",
    "blogImg": "/images/blog-cases/blog_3543108519.jpg",
    "excerpt": "안녕하세요 디디에어컨입니다. 오늘작업은은 파주 B금고 LG 4WAY 시스컨 에어컨 4대 설치 완료했습니다 파주 B금고 현장 들어갔습니다. 신축 공장이라 골조만 서 있는 상태더라고요. 25평형 2대하고 15평형 2대, 총 4대 LG 4WAY 설치하는 현장이었어요. 12월 5일 첫 날 작업 시작했는데 공장 규모가 꽤 커서 렌탈 고소작업대 불러야 했습니다. 층고가 높으니까 위치 선정이 제일 중요하더라고요. 공간이 넓어서 기류 흐름 제대로 안 잡으면 온도 편차 생기거든요. 레이저 레벨기로 위치 마킹하고 ",
    "blogLink": "https://blog.naver.com/ddinair/224170544652?fromRss=true&trackingCode=rss"
  },
  {
    "img": "blog_4763521834.jpg",
    "date": "2026.01",
    "place": "남양주 진건읍 A스튜디오",
    "spec": "삼성 냉난방기 40평형 설치 - 소음과 진동을 잡는 섬세한 시공",
    "type": "기타",
    "blogImg": "/images/blog-cases/blog_4763521834.jpg",
    "excerpt": "진건읍 음악 스튜디오 현장 다녀왔습니다 추운데 진건읍 사릉로까지 나갔어요. A스튜디오라고 음악 작업실인데, 40평형 삼성 스탠드 설치 요청 들어와서요. 근데 일반 상가랑 다르더라고요. 음악 하는 곳이라 소음이랑 진동 완전 예민하게 봐야 한대요. 녹음 중에 에어컨 소리 들어가면 안 된다고. 그래서 이번 현장은 더 신경 써서 했습니다. 실내기부터 자리 잡았어요 도착해서 보니까 인테리어가 블랙으로 깔끔하게 돼있더라고요. 냉난방기 설치해도 분위기 안 깨지게 위치 잡는 게 중요했어요. 공기 순환도 생각해야",
    "blogLink": "https://blog.naver.com/ddinair/224164441219?fromRss=true&trackingCode=rss"
  },
  {
    "img": "blog_2110531404.jpg",
    "date": "2026.01",
    "place": "한남동 쇼룸",
    "spec": "삼성 시스템에어컨 6마력 시공 - 붉은 벽돌과 노출 콘크리트, 배관의 미학을 담다",
    "type": "기타",
    "blogImg": "/images/blog-cases/blog_2110531404.jpg",
    "excerpt": "인테리어의 완성도가 곧 브랜드의 가치가 되는 쇼룸 및 플래그십 스토어에서, 노출 천장 시스템에어컨 시공은 단순한 냉난방기 설치를 넘어선 공간 엔지니어링입니다. 배관이 그대로 드러나는 만큼 한 치의 오차도 허용되지 않는 고도의 기술력이 요구됩니다. 이번 현장은 서울 용산구 한남동에 위치한 구옥 리모델링 쇼룸으로, 붉은 벽돌과 거친 노출 콘크리트의 조화를 해치지 않도록 정밀한 배관 라인 설계와 실내기 안착을 진행 중인 시공 사례입니다. [시공 전]: 현장 진단 및 기류/배관 설계 해당 현장은 한남동의",
    "blogLink": "https://blog.naver.com/ddinair/224162963005?fromRss=true&trackingCode=rss"
  },
  {
    "img": "blog_2485619995.jpg",
    "date": "2026.01",
    "place": "수원 광교 상가 매립 덕트 작업",
    "spec": "",
    "type": "기타",
    "blogImg": "/images/blog-cases/blog_2485619995.jpg",
    "excerpt": "오늘은 수원 광교에 있는 상가 현장에 다녀왔습니다. 기존에 사용하시던 LG 12마력 대형 시스템 에어컨 실내기 매립 덕트 작업입니다. 눈에 보이지 않는 공간에서 기류를 제어하고 응축수를 배출해야 하므로, 철저한 사전 설계와 원칙 시공이 수반되지 않으면 심각한 하자로 직결됩니다. 이번 현장은 수원 광교에 위치한 O상가로, 기존에 운용 중이던 LG 12마력 대형 매립덕트 실내기를 새로운 위치로 이전 설치한 정밀 시공 사례입니다. 1. 이전 설치의 기본, 배선 점검부터 현장 도착해서 가장 먼저 단자대부",
    "blogLink": "https://blog.naver.com/ddinair/224161850548?fromRss=true&trackingCode=rss"
  },
  {
    "img": "blog_7594634403.jpg",
    "date": "2026.01",
    "place": "부천 소사구 음식점.",
    "spec": "LG 25평형 4WAY 냉난방기 교체!  현장",
    "type": "4WAY",
    "blogImg": "/images/blog-cases/blog_7594634403.jpg",
    "excerpt": "안녕하세요 디디에어컨입니다. 12월 23일에 부천 소사구 짬뽕집 다녀왔어요. 연말연초라 일이 많아서 늦게 올리네요 도착해서 보니까 짬뽕집인데 손님들 많이 오시는곳 같더라고요. 근데 에어컨이 오래되서 교체하신다고. 배관을 재사용하여 설치비를 줄여 합리적인 가격으로 설치했다습니다 철거작업실시 새 제품 달았습니다. LG 25평짜리 4WAY 천장형이에요. 배관은 옛날거 쓰는데 체결은 새로하는거니까 토크렌치로 빡세게 조였어요. 이거 안하면나중에가스새요. 화이트 천장이랑 잘 어울리네요. 그런데말이죠. 실외기",
    "blogLink": "https://blog.naver.com/ddinair/224156306794?fromRss=true&trackingCode=rss"
  },
  {
    "img": "blog_8501942560.jpg",
    "date": "2026.01",
    "place": "남양주 다산 신도시 아파트 입주전 배관작업 현장 + 시스템에어컨 선배관(단배관) 공사",
    "spec": "",
    "type": "기타",
    "blogImg": "/images/blog-cases/blog_8501942560.jpg",
    "excerpt": "천장이 완전히 개방된 인테리어 초기 단계에 투입되었습니다. 소방 배관, 환기 덕트, 전기 트레이가 얽혀 있는 복잡한 천장 내부 구조를 정확히 파악하는 것이 우선입니다. 실내기가 안착될 위치부터 실외기실까지의 동선을 최단 거리로 계산하여 배관 길이를 산출합니다. 1m의 오차도 냉매 순환 효율 저하로 직결되므로, 현장 구조에 맞춘 정밀한 분기점 설계와 배관 라우팅(Routing)을 확정했습니다. [본론] 엔지니어링 솔루션: 하자를 원천 차단하는 무결점 시공 배관 처짐 현상은 냉매 흐름을 방해하고 배관",
    "blogLink": "https://blog.naver.com/ddinair/224153824360?fromRss=true&trackingCode=rss"
  },
  {
    "img": "blog_1562050837.jpg",
    "date": "2026.01",
    "place": "남양주 다산 에이바헤어",
    "spec": "LG 25평형 4WAY 1등급 설치! 미용실 냉난방기 완벽 교체 현장",
    "type": "4WAY",
    "blogImg": "/images/blog-cases/blog_1562050837.jpg",
    "excerpt": "에어컨은 상업 공간의 매출과 직결되는 핵심 설비입니다. 특히 열원 기구 사용이 많은 미용실이나 식당의 경우, 냉난방기의 갑작스러운 고장은 치명적인 영업 손실을 초래합니다. 이번 현장은 기기 노후화로 인한 잦은 고장과 과도한 수리 견적에 직면한 고객을 위해, 근본적인 해결책과 비용 절감 솔루션을 동시에 적용한 시공 사례입니다. [시공 전]: 현장 진단 및 고객 요청사항 해당 현장은 남양주 다산에 위치한 'A헤어' 미용실입니다. 고객께서는 기존 에어컨의 냉매 누설 및 압축기(콤프레셔) 불량으로 타 업",
    "blogLink": "https://blog.naver.com/ddinair/224152620327?fromRss=true&trackingCode=rss"
  },
  {
    "img": "blog_5013851032.jpg",
    "date": "2026.01",
    "place": "일산 한방병원",
    "spec": "삼성 4WAY 청장형에어컨 설치! 병원 시스템에어컨 시공은 디디에어컨에 맡기세요.",
    "type": "4WAY",
    "blogImg": "/images/blog-cases/blog_5013851032.jpg",
    "excerpt": "안녕하세요, 디디에어컨입니다! 병원 같은 의료 시설, 에어컨은 '의료 시설 전문가'에게 맡겨야 합니다. 병원이나 한의원 같은 의료 시설은 일반 상가나 사무실과는 다릅니다. 환자분들이 계신 공간이기 때문에 위생 관리가 철저해야 하고, 쾌적한 환경이 치료와 회복에 직접적인 영향을 미치죠. 게다가 진료 중에는 소음을 최소화해야 하고, 전기 안전도 일반 공간보다 훨씬 더 신경 써야 합니다. 이번에 소개해드릴 일산 자향한방병원 시공 사례가 바로 그런 경우였습니다. 넓은 대기실과 진료실에 균일한 냉난방이 필",
    "blogLink": "https://blog.naver.com/ddinair/224145547308?fromRss=true&trackingCode=rss"
  },
  {
    "img": "blog_1734539181.jpg",
    "date": "2026.01",
    "place": "성공적인 상가 공간 재탄생!",
    "spec": "LG 시스템에어컨 이전설치 & 냉방 전용 투인원 신규 디디에어컨 (상도동밤술집)",
    "type": "기타",
    "blogImg": "/images/blog-cases/blog_1734539181.jpg",
    "excerpt": "안녕하세요, 고객님의 공간을 디자인하는 남양주 시스템에어컨 설치 전문 업체 디디에어컨(Detail Design Aircon) 대표입니다. 저희는 남양주 본점을 거점으로 경기권 전 지역에 걸쳐 상업용 냉난방기 시공을 전문으로 하며, 정밀한 시스템에어컨 이전설치 기술로 신뢰를 쌓아가고 있습니다. 이번 시공 사례는 서울 상도동 에 위치한 '씨술집' 프로젝트입니다. 기존 냉난방 벽걸이이전설치와 함께, 쾌적한 매장 환경을 위한 LG 30평형 4WAY 천장형 에어컨 및 냉방전용 투윈원 모델을 신규 설치했습니",
    "blogLink": "https://blog.naver.com/ddinair/224132759286?fromRss=true&trackingCode=rss"
  },
  {
    "img": "blog_4647339105.jpg",
    "date": "2025.12",
    "place": "천안 어린이집 천장형에어컨 설치 & 벽걸이 복합 시공! 인버터 냉난방기 시공은 디디에어컨에 맡기세요.",
    "spec": "",
    "type": "벽걸이",
    "blogImg": "/images/blog-cases/blog_4647339105.jpg",
    "excerpt": "1. 서론: 복합 공간, 에어컨은 '복합 전문가'에게 맡겨야 합니다. 사무실, 학원, 어린이집과 같이 여러 공간을 동시에 사용하는 곳은 냉방/난방 요구 사항이 다릅니다. 메인 공간에는 고용량의 남양주시스템에어컨을, 작은 개별 공간에는 벽걸이형을 조합하는 복합 설치가 최적의 해답입니다. 저희 **디디에어컨(Detail Design Aircon)**은 남양주 본점을 기반으로 이러한 고난도 복합 시공을 정확한 설계와 깔끔한 마감으로 직접 수행하는 남양주에어컨설치 전문 업체입니다. 오늘 소개해 드릴 사례",
    "blogLink": "https://blog.naver.com/ddinair/224122360310?fromRss=true&trackingCode=rss"
  },
  {
    "img": "blog_8525914288.jpg",
    "date": "2025.12",
    "place": "아산부동산 사무실 25평형 4way 1조 설치/ 완벽한 디테일, 천장형에어컨 설치는 디디에어컨이 답입니다.(상업용 인버터 냉난방기 시공 사례)",
    "spec": "",
    "type": "기타",
    "blogImg": "/images/blog-cases/blog_8525914288.jpg",
    "excerpt": "1. 서론: '보이지 않는 곳'의 디테일이 성능을 결정합니다 에어컨은 한 번 설치하면 10년 이상 사용하는 고가 제품입니다. 특히 상업 공간에 설치하는 시스템에어컨 설치는 건물 구조와 냉난방 효율을 모두 고려한 정확한 설계가 필수입니다. 잘못된 시공은 누수, 성능 저하는 물론, 전기 안전 문제로 이어질 수 있기 때문입니다. 저희 **디디에어컨(Detail Design Aircon)**은 남양주 본점을 기반으로 남양주시스템에어컨 설치 분야에서 신뢰를 쌓아온 전문가입니다. 가정용 벽걸이부터 대형 상업",
    "blogLink": "https://blog.naver.com/ddinair/224122330051?fromRss=true&trackingCode=rss"
  },
  {
    "img": "blog_9519795798.jpg",
    "date": "2025.12",
    "place": "고덕롯데캐슬 사무실  남양주시스템에어컨 급 시공!",
    "spec": "LG 25평형 4WAY 냉난방 1조 설치 디디에어컨",
    "type": "4WAY",
    "blogImg": "/images/blog-cases/blog_9519795798.jpg",
    "excerpt": "1. 서론: 왜 에어컨은 '전문 시공'이 필요한가요? 가정용 에어컨 설치부터 대규모 남양주시스템에어컨 시공까지, 에어컨은 단순히 전원을 꽂는 제품이 아닌 '정확한 설치 기술'이 필요한 공사입니다. 특히 여름철 냉방 성능 문제나 겨울철 난방 효율 저하는 90% 이상이 잘못된 설치에서 비롯됩니다. 저희 **디디에어컨(Detail Design Aircon)**은 남양주 본점을 기반으로 남양주, 구리, 의정부는 물론, 수원, 용인 등 경기권 전 지역 출장 시공이 가능한 전문 업체입니다. 'Detail D",
    "blogLink": "https://blog.naver.com/ddinair/224122295676?fromRss=true&trackingCode=rss"
  },
  {
    "img": "blog_1137988451.jpg",
    "date": "2025.12",
    "place": "꼼꼼함의 차이! 남양주시스템에어컨 & 하남시에어컨이전설치",
    "spec": "LG 30 형 4way 냉난방전문 디디에어컨 시공 후기",
    "type": "기타",
    "blogImg": "/images/blog-cases/blog_1137988451.jpg",
    "excerpt": "1. 시공 의뢰 고객님들이 가장 고민하는 것 에어컨 설치, 특히 남양주에어컨이전설치나 규모가 큰 남양주시스템에어컨 시공은 단순한 가전제품 설치 이상의 '기술'과 '경험'을 요구합니다. 잘못된 설치는 냉방 성능 저하는 물론, 누수나 전기 문제로 이어져 큰 비용 손해를 초래할 수 있기 때문입니다. 저희 **디디에어컨(Detail Design Aircon)**은 남양주 본점을 기반으로 오랜 기간 쌓아온 전문성을 바탕으로, 정확한 설계와 깔끔한 마감으로 고객님의 걱정을 덜어드리는 남양주에어컨설치 전문 업",
    "blogLink": "https://blog.naver.com/ddinair/224122261128?fromRss=true&trackingCode=rss"
  },
  {
    "img": "blog_5870538560.jpg",
    "date": "2025.12",
    "place": "LG 36평 4WAY 냉난방기, 의정부 호프집 깔끔 시공 사례 (디디에어컨)",
    "spec": "",
    "type": "4WAY",
    "blogImg": "/images/blog-cases/blog_5870538560.jpg",
    "excerpt": "1. 시공 사례: 의정부동 상업 공간 LG 36평 4WAY 냉난방기 설치 이번 시공은 경기도 의정부동에 위치한 상업 공간(술집 '러포')에 LG 36평 4WAY 시스템 냉난방기 1조를 설치한 사례입니다. 2. 꼼꼼한 설치 및 제품 사양 디테일 A. 실내기 & 실외기 제품 사양 설치된 시스템은 실내기 모델 TNW1302A2UR와 실외기 모델 TUW1302A2SR의 조합으로, 뛰어난 성능과 효율을 자랑합니다. 정격 용량: 정격냉방능력: 13,000 W 정격난방능력: 15,000 W 냉매 정보: 냉매명",
    "blogLink": "https://blog.naver.com/ddinair/224117953235?fromRss=true&trackingCode=rss"
  },
  {
    "img": "blog_6562497677.jpg",
    "date": "2025.12",
    "place": "수원 대형 유치원 4WAY 시스템에어컨 '완벽 이전설치' 후기! (feat. 냉매/배관/전기 전문가 디디에어컨)",
    "spec": "",
    "type": "4WAY",
    "blogImg": "/images/blog-cases/blog_6562497677.jpg",
    "excerpt": "#남양주에어컨설치 #수원에어컨이전설치 #시스템에어컨 #냉난방기설치 #디디에어컨 안녕하세요. 정확한 설계와 꼼꼼한 마감으로 신뢰를 쌓아가는 남양주 에어컨 설치 전문 업체, 디디에어컨(DD AIRCON LAB) 입니다. 저희 디디에어컨은 남양주 본점을 기반으로 구리, 의정부, 수원, 용인 등 경기권 전 지역을 아우르며, 가정집은 물론 공장, 사무실, 학원, 매장 등 모든 업종의 시스템에어컨 및 냉난방기 설치, 이전설치, 유지보수를 대표가 직접 시공하고 있습니다. 오늘은 까다로운 대형 시스템 이전설치 ",
    "blogLink": "https://blog.naver.com/ddinair/224117848409?fromRss=true&trackingCode=rss"
  },
  {
    "img": "blog_3378754488.jpg",
    "date": "2025.12",
    "place": "상봉동 매장 냉난방 시스템에어컨 설치작업 사례",
    "spec": "",
    "type": "기타",
    "blogImg": "/images/blog-cases/blog_3378754488.jpg",
    "excerpt": "안녕하세요 오늘은 서울 상봉동에 위치한 상가건물 현장에서 시스템에어컨 설치작업을 실시하였습니다. 에어컨 설치는 단순히 제품을 걸고 배관을 연결하는 작업이 아닙니다. 건물의 구조를 정확히 이해하고, 제품의 성능을 100% 발휘하도록 정밀하게 설계하는 전문 시공 기술이 필요합니다. 오늘은 서울 상봉동 왁싱샵에서 진행된 LG 25평 4WAY 냉난방 설치 사례를 통해 디디에어컨의 차별화된 시공력을 보여드리겠습니다. 1. 프로젝트 개요: 상봉동 왁싱샵 시스템에어컨 설치 상봉동의 신규 왁싱샵은 고객들에게 쾌",
    "blogLink": "https://blog.naver.com/ddinair/224117517747?fromRss=true&trackingCode=rss"
  },
  {
    "img": "blog_5689018707.jpg",
    "date": "2025.12",
    "place": "평창동 콘서트장 시스템냉난방기 멀티조합",
    "spec": "",
    "type": "멀티",
    "blogImg": "/images/blog-cases/blog_5689018707.jpg",
    "excerpt": "공간과 공기를 디자인하는 남양주 디디에어컨 평창동 콘서트장 시스템에어컨 멀티조합 시공사례 1. 프로젝트 개요 평창동에 위치한 콘서트장은 다양한 문화 행사를 위한 공간으로, 쾌적한 환경을 유지하기 위해 시스템 에어컨 설치가 필수적입니다. 이번 프로젝트는 이러한 필요성을 충족시키기 위해 진행되었습니다. 시스템 에어컨은 공간의 디자인과 기능성을 동시에 고려하여 설치되었으며, 특히 멀티조합 시스템을 통해 효율적인 냉난방이 가능하도록 설계되었습니다. 2. 시공 전 준비 과정 시공 전, 공간의 구조와 사용 ",
    "blogLink": "https://blog.naver.com/ddinair/224102839354?fromRss=true&trackingCode=rss"
  }
]